pyFoF/__init__.py
pyFoF/data_handling.py
pyFoF/edge_data.txt
pyFoF/experiment.py
pyFoF/fof.py
pyFoF/graph_theory.py
pyFoF/group.py
pyFoF/group_catalog.fits
pyFoF/metrics.py
pyFoF/report.py
pyFoF/speck_handling.py
pyFoF/survey.py
pyFoF/utils.py
fofpy-1.0.12.dist-info/LICENSE
fofpy-1.0.12.dist-info/METADATA
fofpy-1.0.12.dist-info/WHEEL
fofpy-1.0.12.dist-info/RECORD
