Metadata-Version: 2.1
Name: fofpy
Version: 1.0.12
Summary: Python package to perform group finding in redshift surveys.
Home-page: https://github.com/TrystanScottLambert/pyFoF
Author: Trystan Scott Lambert
Author-email: trystanscottlambert@gmail.com
Maintainer: Victor Gueorguiev Gueorguiev
Maintainer-email: victor.gueorg@gmail.com
Requires-Python: >=3.10,<3.12
Classifier: License :: OSI Approved :: MIT License
Classifier: Operating System :: OS Independent
Classifier: Programming Language :: Python :: 3
Classifier: Programming Language :: Python :: 3.10
Classifier: Programming Language :: Python :: 3.11
Requires-Dist: astropy (==5.2)
Requires-Dist: matplotlib (==3.6.2)
Requires-Dist: networkx (==3.0)
Requires-Dist: numpy (==1.23.5)
Requires-Dist: pandas (==1.5.2)
Requires-Dist: rich (==13.3.1)
Requires-Dist: scikit-learn (==1.2.1)
Requires-Dist: scipy (==1.10.0)
Requires-Dist: tqdm (==4.64.1)
Requires-Dist: typing-extensions (==4.4.0)
Project-URL: Repository, https://github.com/TrystanScottLambert/pyFoF
Project-URL: issues, https://github.com/TrystanScottLambert/pyFoF/issues
